infnlp/__init__.py
infnlp/nlp.py
infnlp-0.0.3.dist-info/METADATA
infnlp-0.0.3.dist-info/WHEEL
infnlp-0.0.3.dist-info/top_level.txt
infnlp-0.0.3.dist-info/RECORD
